covid19/__init__.py
covid19/main.py
covid19-1.0.0.dist-info/METADATA
covid19-1.0.0.dist-info/WHEEL
covid19-1.0.0.dist-info/top_level.txt
covid19-1.0.0.dist-info/RECORD
